README.md
ptonppl/__init__.py
ptonppl/__main__.py
ptonppl/abstract.py
ptonppl/constants.py
ptonppl/control.py
ptonppl/ldap.py
ptonppl/ldapcmd.py
ptonppl/requests.py
ptonppl/webdir.py
ptonppl-1.0.2.dist-info/entry_points.txt
ptonppl-1.0.2.dist-info/LICENSE
ptonppl-1.0.2.dist-info/WHEEL
ptonppl-1.0.2.dist-info/METADATA
ptonppl-1.0.2.dist-info/RECORD
