Metadata-Version: 2.1
Name: ptonppl
Version: 1.0.2
Summary: An integration package to lookup Princeton campus users.
Home-page: https://github.com/jlumbroso/ptonppl
License: LGPL-3.0-or-later
Keywords: Princeton,directory
Author: Jérémie Lumbroso
Author-email: lumbroso@cs.princeton.edu
Requires-Python: >=3.6,<4.0
Classifier: Development Status :: 5 - Production/Stable
Classifier: License :: OSI Approved :: GNU Lesser General Public License v3 or later (LGPLv3+)
Classifier: Programming Language :: Python :: 3
Classifier: Programming Language :: Python :: 3.6
Classifier: Programming Language :: Python :: 3.7
Classifier: Programming Language :: Python :: 3.8
Classifier: Programming Language :: Python :: 3.9
Classifier: Topic :: Software Development :: Libraries :: Python Modules
Requires-Dist: backoff (>=1.10.0,<2.0.0)
Requires-Dist: bs4 (>=0.0.1,<0.0.2)
Requires-Dist: click (>=7.1.2,<8.0.0)
Requires-Dist: click-option-group (>=0.5.1,<0.6.0)
Requires-Dist: click_help_colors (>=0.8,<0.9)
Requires-Dist: python-ldap (>=3.3.1,<4.0.0)
Requires-Dist: requests (>=2.24.0,<3.0.0)
Project-URL: Repository, https://github.com/jlumbroso/ptonppl
